{
  "package-id": "icare",
  "title": "CodeX Implementation Guide: ICAREdata",
  "canonical": "http://mcodeinitiative.org/codex/us/icare",
  "introduction": "The ICAREdata project supports the prospective collection of high quality real-world data to enable clinical oncology research.",
  "list": [
    {
      "version": "current",
      "desc": "Continuous Integration Build (latest in version control)",
      "path": "http://mcodeinitiative.org/codex/us/icare",
      "status": "ci-build",
      "current": true
    },
    {
      "version": "1.0.0",
      "fhirversion": "4.0.1",
      "date": "2099-01-01",
      "desc": "Initial Draft Release",
      "path": "http://mcodeinitiative.org/codex/us/icare",
      "status": "ballot",
      "sequence": "STU 1"
    }
  ]
}
